WeiruanGuanfangFZhinan20171224/README.md
WeiruanGuanfangFZhinan20171224/__init__.py
WeiruanGuanfangFZhinan20171224/__main__.py
WeiruanGuanfangFZhinan20171224/file.epub
WeiruanGuanfangFZhinan20171224/index.html
WeiruanGuanfangFZhinan20171224/css/__init__.py
WeiruanGuanfangFZhinan20171224/css/annotations.css
WeiruanGuanfangFZhinan20171224/css/main.css
WeiruanGuanfangFZhinan20171224/css/normalize.css
WeiruanGuanfangFZhinan20171224/css/popup.css
WeiruanGuanfangFZhinan20171224/font/__init__.py
WeiruanGuanfangFZhinan20171224/font/fontello.eot
WeiruanGuanfangFZhinan20171224/font/fontello.svg
WeiruanGuanfangFZhinan20171224/font/fontello.ttf
WeiruanGuanfangFZhinan20171224/font/fontello.woff
WeiruanGuanfangFZhinan20171224/img/__init__.py
WeiruanGuanfangFZhinan20171224/img/annotator-glyph-sprite.png
WeiruanGuanfangFZhinan20171224/img/annotator-icon-sprite.png
WeiruanGuanfangFZhinan20171224/img/apple-touch-icon.png
WeiruanGuanfangFZhinan20171224/img/cancelfullscreen.png
WeiruanGuanfangFZhinan20171224/img/close.png
WeiruanGuanfangFZhinan20171224/img/fullscreen.png
WeiruanGuanfangFZhinan20171224/img/loader.gif
WeiruanGuanfangFZhinan20171224/img/menu-icon.png
WeiruanGuanfangFZhinan20171224/img/save.png
WeiruanGuanfangFZhinan20171224/img/saved.png
WeiruanGuanfangFZhinan20171224/img/settings-s.png
WeiruanGuanfangFZhinan20171224/img/settings.png
WeiruanGuanfangFZhinan20171224/img/star.png
WeiruanGuanfangFZhinan20171224/js/__init__.py
WeiruanGuanfangFZhinan20171224/js/epub.js
WeiruanGuanfangFZhinan20171224/js/epub.min.js
WeiruanGuanfangFZhinan20171224/js/epub.min.map
WeiruanGuanfangFZhinan20171224/js/hooks.min.js
WeiruanGuanfangFZhinan20171224/js/hooks.min.map
WeiruanGuanfangFZhinan20171224/js/reader.js
WeiruanGuanfangFZhinan20171224/js/reader.js.map
WeiruanGuanfangFZhinan20171224/js/reader.min.js
WeiruanGuanfangFZhinan20171224/js/reader.min.map
WeiruanGuanfangFZhinan20171224/js/hooks/__init__.py
WeiruanGuanfangFZhinan20171224/js/hooks/extensions/__init__.py
weiruan_guanfang_f_zhinan_20171224-2024.3.2.0.dist-info/METADATA
weiruan_guanfang_f_zhinan_20171224-2024.3.2.0.dist-info/WHEEL
weiruan_guanfang_f_zhinan_20171224-2024.3.2.0.dist-info/entry_points.txt
weiruan_guanfang_f_zhinan_20171224-2024.3.2.0.dist-info/top_level.txt
weiruan_guanfang_f_zhinan_20171224-2024.3.2.0.dist-info/RECORD
